winzy_laptop_battery/__init__.py
winzy_laptop_battery-0.0.1.dist-info/LICENSE
winzy_laptop_battery-0.0.1.dist-info/METADATA
winzy_laptop_battery-0.0.1.dist-info/WHEEL
winzy_laptop_battery-0.0.1.dist-info/entry_points.txt
winzy_laptop_battery-0.0.1.dist-info/top_level.txt
winzy_laptop_battery-0.0.1.dist-info/RECORD
