Metadata-Version: 2.1
Name: winzy-laptop-battery
Version: 0.0.1
Summary: Get laptop battery info and warn if asked
Author: Sukhbinder Singh
License: Apache-2.0
Project-URL: Homepage, https://github.com/sukhbinder/winzy-laptop-battery
Project-URL: Changelog, https://github.com/sukhbinder/winzy-laptop-battery/releases
Project-URL: Issues, https://github.com/sukhbinder/winzy-laptop-battery/issues
Project-URL: CI, https://github.com/sukhbinder/winzy-laptop-battery/actions
Classifier: License :: OSI Approved :: Apache Software License
License-File: LICENSE
Requires-Dist: winzy
Requires-Dist: psutil
Requires-Dist: winsay ; platform_system == "Windows"
Provides-Extra: test
Requires-Dist: pytest ; extra == 'test'
